<?xml version="1.0" encoding="UTF-8"?>
<kingcms>
	<title>单页面</title>
	<author>Sin.CS</author>
	<source>KingCMS.com</source>
	<mail>KingCMS@Gmail.com</mail>
	<common>
		<add>添加单页面</add>
		<createmap>生成单页面Sitemaps</createmap>
	</common>
	<list>
		<id>ID</id>
		<name>页面名称</name>
		<manage>操作</manage>
		<path>路径</path>
	</list>
	<label>
		<name>页面名称</name>
		<title>页面标题 (&amp;lt;title&amp;gt;中的内容)</title>
		<description>简述</description>
		<keyword>关键字 (关键字之间用英文逗号分开)</keyword>
		<path>页面路径 (不支持 &amp;lt\:*?"|,;&amp;gt; 字符，不能以/开始或结束，格式：dir1/dir2 留空则为首页)</path>
		<content>页面内容</content>
		<template1>外部模板</template1>
		<template2>内部模板</template2>
		<isupdate>实时更新</isupdate>
		<isupdate1>选择，则实时更新，需要和{king:onepage#update/}标签配合使用</isupdate1>
	</label>
	<check>
		<name>页面名称不能为空</name>
		<title>页面标题不能为空</title>
		<path>页面路径不能为空</path>
		<path1>页面路径格式错误</path1>
		<path2>页面路径重复，请另取名</path2>
		<content>页面内容不能为空</content>
		<keyword>关键字不能超过50个字符</keyword>
		<description>简述不能超过250个字符</description>
	</check>
	<flo>
		<select>请选择一个栏目</select>
		<createok>成功生成指定的栏目</createok>
		<createmapok>成功生成单页面地图</createmapok>
		<deleteok>成功删除指定的栏目</deleteok>
		<invalid>您指定的栏目已经被删除！请不要重复删除</invalid>
	</flo>
	<alert>
		<saveok>保存成功，若添加新的页面，请按确定！</saveok>
	</alert>
</kingcms>